mortgage_roadmap/__init__.py
mortgage_roadmap/base/__init__.py
mortgage_roadmap/core/__init__.py
mortgage_roadmap-0.1.3.data/data/requirements.txt
mortgage_roadmap-0.1.3.data/data/.git/config
mortgage_roadmap-0.1.3.dist-info/LICENSE
mortgage_roadmap-0.1.3.dist-info/METADATA
mortgage_roadmap-0.1.3.dist-info/WHEEL
mortgage_roadmap-0.1.3.dist-info/top_level.txt
mortgage_roadmap-0.1.3.dist-info/RECORD
