Metadata-Version: 2.1
Name: mortgage_roadmap
Version: 0.1.3
Summary: mortgage_calculator: 
Home-page: https://github.com/R-Rijnbeek/mortgage_roadmap
Author: Robert Rijnbeek
Author-email: robert270384@gmail.com
Project-URL: Bug Tracker, https://github.com/R-Rijnbeek/mortgage_roadmap/issues
Classifier: Programming Language :: Python :: 3
Classifier: License :: OSI Approved :: MIT License
Classifier: Operating System :: OS Independent
Requires-Python: >=3.10
License-File: LICENSE
Requires-Dist: sympy
Requires-Dist: basic-decorators
